MANIFEST.in
README.md
setup.py
dipor/__init__.py
dipor/jinja_changes.py
dipor/main.py
dipor/renderer.py
dipor/server.py
dipor/settings.py
dipor.egg-info/PKG-INFO
dipor.egg-info/SOURCES.txt
dipor.egg-info/dependency_links.txt
dipor.egg-info/entry_points.txt
dipor.egg-info/requires.txt
dipor.egg-info/top_level.txt
dipor/__pycache__/__init__.cpython-36.pyc
dipor/__pycache__/jinja_changes.cpython-36.pyc
dipor/__pycache__/main.cpython-36.pyc
dipor/__pycache__/server.cpython-36.pyc
dipor/cmd/__init__.py
dipor/cmd/start.py
dipor/cmd/__pycache__/__init__.cpython-36.pyc
dipor/cmd/__pycache__/start.cpython-36.pyc
dipor/jinja/__init__.py
dipor/jinja/extensions.py
dipor/jinja/__pycache__/__init__.cpython-36.pyc
dipor/jinja/__pycache__/extensions.cpython-36.pyc
dipor/markdown_extensions/__init__.py
dipor/markdown_extensions/class_wrapper.py
dipor/markdown_extensions/__pycache__/__init__.cpython-36.pyc
dipor/markdown_extensions/__pycache__/class_wrapper.cpython-36.pyc
dipor/readers/__init__.py
dipor/readers/base.py
dipor/readers/markdown.py
dipor/readers/__pycache__/__init__.cpython-36.pyc
dipor/readers/__pycache__/base.cpython-36.pyc
dipor/readers/__pycache__/markdown.cpython-36.pyc
dipor/starters/__init__.py
dipor/starters/bigbang/content/common.md
dipor/starters/bigbang/src/index.html
dipor/starters/quickstart/content/common.md
dipor/starters/quickstart/content/meta.md
dipor/starters/quickstart/content/about/common.md
dipor/starters/quickstart/content/blog/common.md
dipor/starters/quickstart/content/blog/_branches/bieber/main.md
dipor/starters/quickstart/content/blog/_branches/bieber/meta.md
dipor/starters/quickstart/content/blog/_branches/miller/main.md
dipor/starters/quickstart/content/blog/_branches/miller/meta.md
dipor/starters/quickstart/src/404.html
dipor/starters/quickstart/src/index.html
dipor/starters/quickstart/src/_components/footer.co
dipor/starters/quickstart/src/_components/header.co
dipor/starters/quickstart/src/about/index.html
dipor/starters/quickstart/src/about/_components/footer.co
dipor/starters/quickstart/src/about/_components/header.co
dipor/starters/quickstart/src/blog/index.html
