Metadata-Version: 1.1
Name: dipor
Version: 0.2.0
Summary: Static Site Generator written in Python for ease of processes
Home-page: https://github.com/vidhibagadia/dipor
Author: Vidh Bagadia
Author-email: vidbagadia@gmail.com
License: MIT
Keywords: static site generator staticsitegenerator python jinja
Platform: UNKNOWN
Classifier: License :: OSI Approved :: MIT License
Classifier: Programming Language :: Python :: 3.6
